aplicacion_ventas_hflores-0.1.0.dist-info/licenses/LICENCE
tests/__init__.py
tests/test_aplicacion_ventas.py
aplicacion_ventas_hflores-0.1.0.dist-info/METADATA
aplicacion_ventas_hflores-0.1.0.dist-info/WHEEL
aplicacion_ventas_hflores-0.1.0.dist-info/top_level.txt
aplicacion_ventas_hflores-0.1.0.dist-info/RECORD
